rbutils
