Metadata-Version: 1.0
Name: rbutils
Version: 2.3.0
Summary: python 常用的工具
Home-page: https://github.com/Adenialzz/SongUtils
Author: robin
Author-email: robin.seu@foxmail.com
License: MIT Licence
Keywords: pip
Platform: any
